legos.markov-0.1.1-py3.6-nspkg.pth
legos/markov.py
legos.markov-0.1.1.dist-info/METADATA
legos.markov-0.1.1.dist-info/RECORD
legos.markov-0.1.1.dist-info/WHEEL
legos.markov-0.1.1.dist-info/namespace_packages.txt
legos.markov-0.1.1.dist-info/top_level.txt
