Metadata-Version: 2.1
Name: legos.markov
Version: 0.1.1
Summary: Lego for organizing text and generating markoved responses
Home-page: https://github.com/Legobot/legos.markov
Author: fraq
Author-email: UNKNOWN
License: MIT
Platform: UNKNOWN
Classifier: License :: OSI Approved :: MIT License
Classifier: Programming Language :: Python :: 3
Classifier: Development Status :: 4 - Beta
Requires-Dist: legobot (<=2.0.0,>=1.2.1)
Requires-Dist: markovify
Requires-Dist: nltk
